publicprojectexample/__init__.py
publicprojectexample/pdf2image.py
publicprojectexample/pdf2text.py
publicprojectexample-1.1.dist-info/LICENSE
publicprojectexample-1.1.dist-info/METADATA
publicprojectexample-1.1.dist-info/WHEEL
publicprojectexample-1.1.dist-info/top_level.txt
publicprojectexample-1.1.dist-info/RECORD
